retrival/__init__.py
retrival/search_engine.py
retrival/utils.py
retrival-1.0.3.dist-info/licenses/LICENSE
retrival-1.0.3.dist-info/METADATA
retrival-1.0.3.dist-info/WHEEL
retrival-1.0.3.dist-info/top_level.txt
retrival-1.0.3.dist-info/RECORD
