Metadata-Version: 2.4
Name: retrival
Version: 1.0.3
Summary: Just for BM25
Home-page: https://github.com/skykiseki/retrival
Author: Wei, Zhihui
Author-email: evelinesdd@qq.com
License: MIT
Keywords: retrival
Classifier: Intended Audience :: Developers
Classifier: License :: OSI Approved :: MIT License
Classifier: Operating System :: OS Independent
Classifier: Natural Language :: Chinese (Simplified)
Classifier: Natural Language :: Chinese (Traditional)
Classifier: Programming Language :: Python
Classifier: Programming Language :: Python :: 3.8
Classifier: Topic :: Text Processing
Classifier: Topic :: Text Processing :: Indexing
Classifier: Topic :: Text Processing :: Linguistic
Requires-Python: >=3.8
License-File: LICENSE
Requires-Dist: scikit-learn>=1.0
Requires-Dist: jieba
Requires-Dist: indxr<=0.1.4
Requires-Dist: jsonlines
Requires-Dist: numba>=0.54.1
Dynamic: author
Dynamic: author-email
Dynamic: classifier
Dynamic: description
Dynamic: description-content-type
Dynamic: home-page
Dynamic: keywords
Dynamic: license
Dynamic: license-file
Dynamic: requires-dist
Dynamic: requires-python
Dynamic: summary
